{
    "hybrid_features": [
        "F1923",
        "F3811",
        "F3487",
        "F3889",
        "F2752",
        "F3806",
        "F2678",
        "F2782",
        "F3240",
        "F2890",
        "F2737",
        "F1041",
        "F1814",
        "F2938",
        "F997",
        "F2956",
        "F3813",
        "F3914",
        "F1594",
        "F2236",
        "F3495",
        "F2488",
        "F120",
        "F1936",
        "F937",
        "F1603",
        "F321",
        "F3894",
        "F1815",
        "F3920",
        "F3824",
        "F3484",
        "F3490",
        "F261",
        "F427",
        "F991",
        "F3900",
        "F18",
        "F996",
        "F2825",
        "F1692",
        "F2137",
        "F531",
        "F1597",
        "F1954",
        "F3043",
        "F3805",
        "F1642",
        "F1746",
        "F510",
        "F1209",
        "F3801",
        "F2786",
        "F1001",
        "F378",
        "F115",
        "F3871",
        "F1921",
        "F1639",
        "F373",
        "F2645",
        "F2686",
        "F2735",
        "F1015",
        "F3887",
        "F463",
        "F670",
        "F2068",
        "F1112",
        "F1058",
        "F2584",
        "F2724",
        "F164",
        "F2885",
        "F1273",
        "F3836",
        "F3868",
        "F3150",
        "F3804",
        "F274",
        "F2282",
        "F2489",
        "F235",
        "F2392",
        "F3526",
        "F3494",
        "F2991",
        "F3872",
        "F3908",
        "F3485",
        "F2796",
        "F54",
        "F1821",
        "F327",
        "F2998",
        "F3921",
        "F465",
        "F1705",
        "F3798",
        "F3348",
        "F3642",
        "F2883",
        "F3891",
        "F408",
        "F3534",
        "F2691",
        "F2242",
        "F3598",
        "F527",
        "F2799",
        "F3105",
        "F2736",
        "F2591",
        "F2078",
        "F2551",
        "F322",
        "F2388",
        "F2586",
        "F2484",
        "F3825",
        "F2772",
        "F3395",
        "F2350",
        "F1057",
        "F3143",
        "F1813",
        "F3886",
        "F951",
        "F1381",
        "F3643",
        "F2082",
        "F374",
        "F1744",
        "F3647",
        "F2527",
        "F1489",
        "F336",
        "F228",
        "F2896",
        "F2999",
        "F366",
        "F2122",
        "F2077",
        "F471",
        "F2070",
        "F3898",
        "F1167",
        "F2640",
        "F270",
        "F2595",
        "F367",
        "F1153",
        "F156",
        "F3287",
        "F3704",
        "F1707",
        "F64",
        "F2582",
        "F2494",
        "F112",
        "F2680",
        "F2848",
        "F2391",
        "F949",
        "F1165",
        "F3907",
        "F3799",
        "F3838"
    ],
    "medians": {
        "F1923": 9868.490566,
        "F3811": 841744.325,
        "F3487": -0.93,
        "F2752": -0.325,
        "F3806": 607818.0,
        "F2678": -0.12,
        "F2782": 0.0,
        "F3240": -1.0,
        "F2890": 46.0,
        "F2737": -0.15,
        "F1041": 0.0,
        "F1814": 864606.48,
        "F2938": 48.0,
        "F997": 30000.0,
        "F2956": 64.0,
        "F3813": 445122.175,
        "F3914": 0.0,
        "F1594": 31.0,
        "F2236": 0.0,
        "F3495": -0.87,
        "F2488": 1.93,
        "F120": 0.64,
        "F1936": 0.0,
        "F937": 0.0,
        "F1603": 621136.07,
        "F321": 1.07,
        "F3894": 34.0,
        "F1815": 760973.99,
        "F3920": 0.0,
        "F3824": 0.46169,
        "F3484": 0.02,
        "F3490": 0.03,
        "F261": 0.31,
        "F427": 1.09,
        "F991": 50000.0,
        "F3900": 0.0,
        "F18": 0.75,
        "F996": 1.0,
        "F2825": -0.42,
        "F1692": 0.0,
        "F2137": 19917.891795,
        "F531": 1.21,
        "F1597": 741636.0,
        "F1954": 0.0,
        "F3043": 87.5,
        "F3805": 1202788.3,
        "F1642": 18.0,
        "F1746": 0.0,
        "F510": 1.0,
        "F1209": 0.0,
        "F3801": 805204.115,
        "F2786": -0.09,
        "F1001": 0.0,
        "F378": 1.02,
        "F115": 0.53,
        "F3871": 153158.03,
        "F1921": 25219.29375,
        "F1639": 137068.0,
        "F373": 1.07,
        "F2645": -0.1,
        "F2686": -0.12,
        "F2735": 0.0,
        "F1015": 0.0,
        "F3887": 94.0,
        "F463": 1.09,
        "F670": 0.0,
        "F2068": 0.095744681,
        "F1112": 908.5,
        "F1058": 123468.89,
        "F2584": -0.1,
        "F2724": -0.185,
        "F164": 0.5,
        "F2885": 44.0,
        "F1273": 123000.0,
        "F3836": 381286.32999999996,
        "F3868": 1.0,
        "F3150": -1.0,
        "F3804": 29.0,
        "F274": 0.29,
        "F2282": 0.57,
        "F2489": 1.48,
        "F235": 0.175,
        "F2392": 0.86,
        "F3526": -0.66,
        "F3494": -0.97,
        "F2991": 71.0,
        "F3872": 156555.5,
        "F3908": 0.0,
        "F3485": -0.26,
        "F2796": -0.16,
        "F54": 0.57,
        "F1821": 720422.81,
        "F327": 1.08,
        "F2998": 76.0,
        "F3921": 0.0,
        "F465": 1.04,
        "F1705": 1106632.0,
        "F3798": 50.5,
        "F3348": -1.0,
        "F3642": 0.16,
        "F2883": 42.0,
        "F408": 1.0,
        "F3534": 0.14,
        "F2691": -0.17,
        "F2242": 0.25,
        "F3598": 0.03,
        "F527": 1.0,
        "F2799": -0.23,
        "F3105": 136.0,
        "F2736": 0.0,
        "F2591": -0.15,
        "F2078": 544.8564356,
        "F2551": -0.22,
        "F322": 1.06,
        "F2388": 0.66,
        "F2586": -0.13,
        "F2484": 2.44,
        "F3825": 0.497485,
        "F2772": -0.45,
        "F3395": -1.0,
        "F2350": 0.57,
        "F1057": 199000.0,
        "F3143": 80.0,
        "F1813": 1627154.255,
        "F951": 90000.0,
        "F1381": 166109.5,
        "F3643": -0.34,
        "F2082": 0.0,
        "F374": 1.08,
        "F1744": 4.0,
        "F3647": -0.91,
        "F2527": -0.04,
        "F1489": 199999.0,
        "F336": 1.0,
        "F228": 0.43,
        "F2896": 43.0,
        "F2999": 69.0,
        "F366": 1.0,
        "F2122": 0.0,
        "F2077": 3253.267465,
        "F471": 1.12,
        "F2070": 0.0,
        "F3898": 3.0,
        "F1167": 100000.0,
        "F2640": 0.0,
        "F270": 0.41,
        "F2595": -0.06,
        "F367": 1.1,
        "F1153": 0.0,
        "F156": 0.61,
        "F3287": -1.0,
        "F3704": -0.95,
        "F1707": 518973.0,
        "F64": 0.7,
        "F2582": 0.0,
        "F2494": 1.55,
        "F112": 0.67,
        "F2680": -0.08,
        "F2848": 38.0,
        "F2391": 0.75,
        "F949": 150000.0,
        "F1165": 205251.5,
        "F3907": 0.0,
        "F3799": 1722078.955,
        "F3838": 123405.595
    },
    "categorical_mappings": {
        "F3889": [
            "G365D",
            "L14D",
            "L180D",
            "L31D",
            "L365D",
            "L7D",
            "L90D"
        ],
        "F3891": [
            "agriculture",
            "housewife",
            "others",
            "retired",
            "salaried",
            "selfemployed",
            "student"
        ],
        "F3886": [
            "Agri Adv",
            "All Others",
            "Corp Adv",
            "Current",
            "Gold Loan",
            "HL",
            "ML",
            "MSME LA TDR",
            "MSME Medium",
            "MSME Micro",
            "MSME Small",
            "PL",
            "Retail LA TDR",
            "Retail Others",
            "Savings",
            "Staff Loans",
            "Term Deposit"
        ]
    },
    "metrics": {
        "xgboost": {
            "recall": 0.8125,
            "precision": 1.0,
            "f1_score": 0.896551724137931,
            "pr_auc": 0.9404017857142857,
            "confusion_matrix": {
                "tp": 13,
                "fp": 0,
                "fn": 3,
                "tn": 1801
            }
        },
        "lightgbm": {
            "recall": 0.8125,
            "precision": 0.9285714285714286,
            "f1_score": 0.8666666666666667,
            "pr_auc": 0.8808197012802277,
            "confusion_matrix": {
                "tp": 13,
                "fp": 1,
                "fn": 3,
                "tn": 1800
            }
        }
    },
    "cohort_medians": {
        "clean_student": {
            "F1923": 6467.052595,
            "F3811": 600000.0,
            "F3487": -0.92,
            "F3889": "G365D",
            "F2752": -0.335,
            "F3806": 469849.0,
            "F2678": -0.15,
            "F2782": 0.0,
            "F3240": -1.0,
            "F2890": 48.0,
            "F2737": -0.2,
            "F1041": 0.0,
            "F1814": 750944.25,
            "F2938": 51.0,
            "F997": 38502.0,
            "F2956": 69.0,
            "F3813": 300000.0,
            "F3914": 0.0,
            "F1594": 34.0,
            "F2236": 0.0,
            "F3495": -0.86,
            "F2488": 1.75,
            "F120": 0.64,
            "F1936": 0.0,
            "F937": 0.0,
            "F1603": 511765.0,
            "F321": 1.08,
            "F3894": 27.0,
            "F1815": 655370.2849999999,
            "F3920": 0.0,
            "F3824": 0.458882,
            "F3484": 0.02,
            "F3490": 0.03,
            "F261": 0.295,
            "F427": 1.11,
            "F991": 39091.5,
            "F3900": 0.0,
            "F18": 0.755,
            "F996": 1.0,
            "F2825": -0.45,
            "F1692": 0.0,
            "F2137": 12423.481365,
            "F531": 1.27,
            "F1597": 585215.46,
            "F1954": 0.0,
            "F3043": 100.0,
            "F3805": 921781.95,
            "F1642": 24.5,
            "F1746": 0.0,
            "F510": 1.0,
            "F1209": 0.0,
            "F3801": 631925.5,
            "F2786": -0.14,
            "F1001": 0.0,
            "F378": 1.025,
            "F115": 0.52,
            "F3871": 139603.305,
            "F1921": 15712.381565,
            "F1639": 100000.0,
            "F373": 1.08,
            "F2645": -0.12,
            "F2686": -0.13,
            "F2735": 0.0,
            "F1015": 0.0,
            "F3887": 112.0,
            "F463": 1.13,
            "F670": 0.0,
            "F2068": 0.08435878399999999,
            "F1112": 1016.0,
            "F1058": 100000.0,
            "F2584": -0.11,
            "F2724": -0.2,
            "F164": 0.5,
            "F2885": 48.0,
            "F1273": 99995.5,
            "F3836": 378730.925,
            "F3868": 1.0,
            "F3150": -1.0,
            "F3804": 31.0,
            "F274": 0.27,
            "F2282": 0.57,
            "F2489": 1.505,
            "F235": 0.2,
            "F2392": 0.86,
            "F3526": -0.69,
            "F3494": -0.95,
            "F2991": 79.0,
            "F3872": 142749.91499999998,
            "F3908": 1.0,
            "F3485": -0.26,
            "F2796": -0.135,
            "F54": 0.58,
            "F1821": 610709.45,
            "F327": 1.08,
            "F2998": 81.0,
            "F3921": 0.0,
            "F465": 1.09,
            "F1705": 899412.19,
            "F3798": 53.5,
            "F3348": -1.0,
            "F3642": 0.315,
            "F2883": 45.0,
            "F3891": "student",
            "F408": 1.0,
            "F3534": 0.29,
            "F2691": -0.22,
            "F2242": 0.36,
            "F3598": 0.02,
            "F527": 1.0,
            "F2799": -0.275,
            "F3105": 145.0,
            "F2736": 0.0,
            "F2591": -0.18,
            "F2078": 726.0397270999999,
            "F2551": -0.23,
            "F322": 1.07,
            "F2388": 0.68,
            "F2586": -0.12,
            "F2484": 2.51,
            "F3825": 0.4976815,
            "F2772": -0.54,
            "F3395": -1.0,
            "F2350": 0.605,
            "F1057": 121127.0,
            "F3143": 96.0,
            "F1813": 1407248.9300000002,
            "F3886": "Savings",
            "F951": 60000.0,
            "F1381": 108038.45,
            "F3643": -0.28,
            "F2082": 0.0,
            "F374": 1.08,
            "F1744": 4.0,
            "F3647": -0.83,
            "F2527": -0.125,
            "F1489": 149999.0,
            "F336": 1.08,
            "F228": 0.43,
            "F2896": 46.5,
            "F2999": 73.0,
            "F366": 1.0,
            "F2122": 0.0,
            "F2077": 3594.035383,
            "F471": 1.13,
            "F2070": 0.0,
            "F3898": 3.0,
            "F1167": 90000.0,
            "F2640": 0.0,
            "F270": 0.42,
            "F2595": -0.05,
            "F367": 1.12,
            "F1153": 0.0,
            "F156": 0.62,
            "F3287": -1.0,
            "F3704": -0.95,
            "F1707": 405375.4,
            "F64": 0.71,
            "F2582": 0.0,
            "F2494": 1.525,
            "F112": 0.66,
            "F2680": -0.1,
            "F2848": 40.0,
            "F2391": 0.8,
            "F949": 100000.0,
            "F1165": 154161.0,
            "F3907": 0.0,
            "F3799": 1334413.9300000002,
            "F3838": 121862.16500000001
        },
        "mule_student": {
            "F1923": 2056.412162,
            "F3811": 123540.2,
            "F3487": -0.72,
            "F3889": "G365D",
            "F2752": -0.5549999999999999,
            "F3806": 109757.0,
            "F2678": -0.075,
            "F2782": 0.0,
            "F3240": -1.0,
            "F2890": 30.0,
            "F2737": -0.19,
            "F1041": 0.0,
            "F1814": 131515.0,
            "F2938": 48.0,
            "F997": 20000.0,
            "F2956": 57.5,
            "F3813": 60867.0,
            "F3914": 0.0,
            "F1594": 28.0,
            "F2236": 0.0,
            "F3495": -0.72,
            "F2488": 0.36,
            "F120": 0.91,
            "F1936": 0.0,
            "F937": 0.0,
            "F1603": 123540.2,
            "F321": 1.19,
            "F3894": 24.0,
            "F1815": 96515.4,
            "F3920": 0.0,
            "F3824": 0.607182,
            "F3484": 0.0,
            "F3490": 0.01,
            "F261": 1.0,
            "F427": 1.08,
            "F991": 1150.0,
            "F3900": 0.0,
            "F18": 0.88,
            "F996": 1.0,
            "F2825": 0.08,
            "F1692": 0.0,
            "F2137": 3083.799532,
            "F531": 1.31,
            "F1597": 123540.2,
            "F1954": 0.0,
            "F3043": 277.0,
            "F3805": 200936.4,
            "F1642": 28.0,
            "F1746": 0.0,
            "F510": 1.0,
            "F1209": 0.0,
            "F3801": 96515.4,
            "F2786": -0.18,
            "F1001": 0.0,
            "F378": 1.02,
            "F115": 0.75,
            "F3871": 30065.82,
            "F1921": 4068.990909,
            "F1639": 1700.0,
            "F373": 1.25,
            "F2645": -0.05,
            "F2686": -0.05,
            "F2735": -0.025,
            "F1015": 0.0,
            "F3887": 98.0,
            "F463": 1.03,
            "F670": 0.0,
            "F2068": 0.034482759,
            "F1112": 0.0,
            "F1058": 25000.0,
            "F2584": -0.1,
            "F2724": -0.185,
            "F164": 1.0,
            "F2885": 21.0,
            "F1273": 23758.0,
            "F3836": 79172.28,
            "F3868": 2.0,
            "F3150": -1.0,
            "F3804": 38.0,
            "F274": 0.58,
            "F2282": 0.0,
            "F2489": 0.46,
            "F235": 0.71,
            "F2392": 0.0,
            "F3526": -0.8,
            "F3494": -0.75,
            "F2991": 73.5,
            "F3872": 30065.82,
            "F3908": 1.0,
            "F3485": -0.19,
            "F2796": -0.16,
            "F54": 0.925,
            "F1821": 96515.4,
            "F327": 1.19,
            "F2998": 57.5,
            "F3921": 0.0,
            "F465": 1.57,
            "F1705": 200936.4,
            "F3798": 63.0,
            "F3348": -1.0,
            "F3642": 0.42,
            "F2883": 41.0,
            "F3891": "student",
            "F408": 1.0,
            "F3534": 0.38,
            "F2691": -0.19,
            "F2242": 0.25,
            "F3598": 0.01,
            "F527": 1.0,
            "F2799": -0.23,
            "F3105": 71.0,
            "F2736": 0.01,
            "F2591": -0.26,
            "F2078": 828.4642857,
            "F2551": -0.35,
            "F322": 1.13,
            "F2388": 0.1,
            "F2586": -0.14,
            "F2484": 1.06,
            "F3825": 0.64633,
            "F2772": -0.5,
            "F3395": -1.0,
            "F2350": 0.09,
            "F1057": 25000.0,
            "F3143": 80.0,
            "F1813": 236393.4,
            "F3886": "Savings",
            "F951": 20000.0,
            "F1381": 24999.0,
            "F3643": -0.48,
            "F2082": 0.0,
            "F374": 1.25,
            "F1744": 2.0,
            "F3647": -1.0,
            "F2527": -0.04,
            "F1489": 36199.0,
            "F336": 1.545,
            "F228": 0.65,
            "F2896": 56.0,
            "F2999": 57.0,
            "F366": 0.99,
            "F2122": 0.0,
            "F2077": 2645.370467,
            "F471": 1.05,
            "F2070": 0.0,
            "F3898": 1.0,
            "F1167": 20000.0,
            "F2640": 0.0,
            "F270": 0.68,
            "F2595": -0.06,
            "F367": 1.12,
            "F1153": 0.0,
            "F156": 1.0,
            "F3287": -1.0,
            "F3704": -0.77,
            "F1707": 75212.6,
            "F64": 0.87,
            "F2582": 0.0,
            "F2494": 0.43000000000000005,
            "F112": 0.93,
            "F2680": -0.36,
            "F2848": 28.5,
            "F2391": 0.0,
            "F949": 23760.0,
            "F1165": 36200.0,
            "F3907": 0.0,
            "F3799": 236393.4,
            "F3838": 30067.23
        },
        "clean_housewife": {
            "F1923": 12190.84135,
            "F3811": 899044.0,
            "F3487": -0.92,
            "F3889": "G365D",
            "F2752": -0.32999999999999996,
            "F3806": 646101.11,
            "F2678": -0.1,
            "F2782": 0.0,
            "F3240": -1.0,
            "F2890": 46.0,
            "F2737": -0.15,
            "F1041": 0.0,
            "F1814": 835523.885,
            "F2938": 40.5,
            "F997": 25000.0,
            "F2956": 60.0,
            "F3813": 488734.28,
            "F3914": 0.0,
            "F1594": 27.0,
            "F2236": 0.0,
            "F3495": -0.86,
            "F2488": 1.99,
            "F120": 0.65,
            "F1936": 0.0,
            "F937": 0.0,
            "F1603": 654270.0,
            "F321": 1.08,
            "F3894": 42.0,
            "F1815": 757093.0,
            "F3920": 0.0,
            "F3824": 0.477025,
            "F3484": 0.02,
            "F3490": 0.03,
            "F261": 0.33,
            "F427": 1.09,
            "F991": 52195.0,
            "F3900": 0.0,
            "F18": 0.81,
            "F996": 1.0,
            "F2825": -0.48,
            "F1692": 0.0,
            "F2137": 25051.314645,
            "F531": 1.22,
            "F1597": 812011.0,
            "F1954": 0.0,
            "F3043": 77.0,
            "F3805": 1245997.82,
            "F1642": 14.0,
            "F1746": 0.0,
            "F510": 1.0,
            "F1209": 0.0,
            "F3801": 819853.3,
            "F2786": -0.09,
            "F1001": 0.0,
            "F378": 1.09,
            "F115": 0.53,
            "F3871": 129083.09,
            "F1921": 34431.86667,
            "F1639": 132000.0,
            "F373": 1.065,
            "F2645": -0.095,
            "F2686": -0.13,
            "F2735": 0.0,
            "F1015": 0.0,
            "F3887": 85.0,
            "F463": 1.08,
            "F670": 0.0,
            "F2068": 0.091784339,
            "F1112": 1460.0,
            "F1058": 146000.0,
            "F2584": -0.09,
            "F2724": -0.11,
            "F164": 0.53,
            "F2885": 36.0,
            "F1273": 129999.0,
            "F3836": 305069.05,
            "F3868": 1.0,
            "F3150": -1.0,
            "F3804": 23.0,
            "F274": 0.33,
            "F2282": 0.5,
            "F2489": 1.48,
            "F235": 0.14,
            "F2392": 0.92,
            "F3526": -0.73,
            "F3494": -0.98,
            "F2991": 66.0,
            "F3872": 129986.72,
            "F3908": 0.0,
            "F3485": -0.26,
            "F2796": -0.24,
            "F54": 0.6,
            "F1821": 732612.365,
            "F327": 1.1,
            "F2998": 74.5,
            "F3921": 0.0,
            "F465": 1.02,
            "F1705": 1154340.0,
            "F3798": 43.0,
            "F3348": -1.0,
            "F3642": 0.12,
            "F2883": 38.0,
            "F3891": "housewife",
            "F408": 1.0,
            "F3534": 0.09,
            "F2691": -0.12,
            "F2242": 0.01,
            "F3598": 0.02,
            "F527": 1.0,
            "F2799": -0.33,
            "F3105": 131.5,
            "F2736": 0.0,
            "F2591": -0.18,
            "F2078": 475.7529925,
            "F2551": -0.23,
            "F322": 1.07,
            "F2388": 0.62,
            "F2586": -0.13,
            "F2484": 2.55,
            "F3825": 0.507057,
            "F2772": -0.5,
            "F3395": -1.0,
            "F2350": 0.49,
            "F1057": 200000.0,
            "F3143": 69.0,
            "F1813": 1565882.25,
            "F3886": "Savings",
            "F951": 83607.0,
            "F1381": 172700.0,
            "F3643": -0.36,
            "F2082": 0.0,
            "F374": 1.14,
            "F1744": 3.0,
            "F3647": -1.0,
            "F2527": 0.0,
            "F1489": 223410.0,
            "F336": 1.0150000000000001,
            "F228": 0.46,
            "F2896": 42.0,
            "F2999": 67.0,
            "F366": 1.01,
            "F2122": 0.0,
            "F2077": 3183.7005465,
            "F471": 1.13,
            "F2070": 0.0,
            "F3898": 1.0,
            "F1167": 100000.0,
            "F2640": 0.0,
            "F270": 0.41,
            "F2595": -0.02,
            "F367": 1.1,
            "F1153": 0.0,
            "F156": 0.62,
            "F3287": -1.0,
            "F3704": -0.94,
            "F1707": 540422.5,
            "F64": 0.72,
            "F2582": 0.0,
            "F2494": 1.495,
            "F112": 0.705,
            "F2680": -0.05,
            "F2848": 36.0,
            "F2391": 0.8,
            "F949": 158597.0,
            "F1165": 250000.0,
            "F3907": 0.0,
            "F3799": 1725040.6,
            "F3838": 112239.56
        },
        "mule_housewife": {
            "F1923": 5437.916667,
            "F3811": 161839.0,
            "F3487": -0.73,
            "F3889": "G365D",
            "F2752": -0.65,
            "F3806": 197323.19,
            "F2678": -0.34,
            "F2782": -0.05,
            "F3240": -1.0,
            "F2890": 25.0,
            "F2737": -0.2,
            "F1041": 0.0,
            "F1814": 531404.0,
            "F2938": 48.0,
            "F997": 30000.0,
            "F2956": 31.0,
            "F3813": 76618.19,
            "F3914": 0.0,
            "F1594": 15.0,
            "F2236": 1.0,
            "F3495": -0.76,
            "F2488": 1.375,
            "F120": 0.64,
            "F1936": 0.0,
            "F937": 0.0,
            "F1603": 161839.0,
            "F321": 0.94,
            "F3894": 33.0,
            "F1815": 498016.82,
            "F3920": 0.0,
            "F3824": 0.275224,
            "F3484": 0.01,
            "F3490": 0.01,
            "F261": 0.31,
            "F427": 1.51,
            "F991": 89583.0,
            "F3900": 0.0,
            "F18": 0.69,
            "F996": 1.0,
            "F2825": -0.42,
            "F1692": 0.0,
            "F2137": 35497.26966,
            "F531": 1.3,
            "F1597": 161839.0,
            "F1954": 0.0,
            "F3043": 38.0,
            "F3805": 382499.13,
            "F1642": 10.0,
            "F1746": 0.0,
            "F510": 0.41,
            "F1209": 0.0,
            "F3801": 875016.82,
            "F2786": -0.39,
            "F1001": 1.0,
            "F378": 1.02,
            "F115": 0.57,
            "F3871": 29979.04,
            "F1921": 13486.58333,
            "F1639": 89584.0,
            "F373": 0.7,
            "F2645": -0.26,
            "F2686": -0.24,
            "F2735": 0.0,
            "F1015": 0.0,
            "F3887": 120.0,
            "F463": 1.51,
            "F670": 0.0,
            "F2068": 0.166666667,
            "F1112": 25.0,
            "F1058": 89583.0,
            "F2584": 0.0,
            "F2724": 0.21,
            "F164": 0.36,
            "F2885": 44.0,
            "F1273": 89582.0,
            "F3836": 125725.44,
            "F3868": 2.0,
            "F3150": -1.0,
            "F3804": 25.0,
            "F274": 0.225,
            "F2282": 0.75,
            "F2489": 0.84,
            "F235": 1.0,
            "F2392": 2.68,
            "F3526": -0.38,
            "F3494": -0.54,
            "F2991": 31.0,
            "F3872": 29979.04,
            "F3908": 1.0,
            "F3485": -0.29,
            "F2796": -0.16,
            "F54": 0.57,
            "F1821": 289032.52,
            "F327": 0.94,
            "F2998": 44.5,
            "F3921": 0.0,
            "F465": 1.04,
            "F1705": 382499.13,
            "F3798": 36.0,
            "F3348": -1.0,
            "F3642": 0.23,
            "F2883": 16.0,
            "F3891": "housewife",
            "F408": 0.435,
            "F3534": 0.23,
            "F2691": 4.545,
            "F2242": 0.25,
            "F3598": 0.01,
            "F527": 1.0,
            "F2799": -0.23,
            "F3105": 48.0,
            "F2736": -0.03,
            "F2591": 0.48,
            "F2078": 583.3333333,
            "F2551": -0.47,
            "F322": 0.84,
            "F2388": 0.44,
            "F2586": 0.0,
            "F2484": 3.37,
            "F3825": 0.265058,
            "F2772": -0.45,
            "F3395": -1.0,
            "F2350": 0.56,
            "F1057": 89583.0,
            "F3143": 28.0,
            "F1813": 1029420.82,
            "F3886": "Savings",
            "F951": 30000.0,
            "F1381": 89582.0,
            "F3643": 0.05,
            "F2082": 0.0,
            "F374": 0.7,
            "F1744": 5.0,
            "F3647": 0.03,
            "F2527": 0.06,
            "F1489": 289410.0,
            "F336": 1.88,
            "F228": 0.54,
            "F2896": 27.5,
            "F2999": 31.0,
            "F366": 1.0,
            "F2122": 0.068965517,
            "F2077": 6021.25,
            "F471": 1.31,
            "F2070": 0.0,
            "F3898": 0.0,
            "F1167": 218781.0,
            "F2640": -0.02,
            "F270": 0.54,
            "F2595": -0.06,
            "F367": 1.0,
            "F1153": 40000.0,
            "F156": 0.61,
            "F3287": -1.0,
            "F3704": 0.25,
            "F1707": 185175.94,
            "F64": 0.75,
            "F2582": 0.065,
            "F2494": 42.88,
            "F112": 0.64,
            "F2680": -0.08,
            "F2848": 16.0,
            "F2391": 2.68,
            "F949": 89583.0,
            "F1165": 289410.0,
            "F3907": 0.0,
            "F3799": 1783420.82,
            "F3838": 32102.19
        },
        "clean_salaried": {
            "F1923": 11727.11146,
            "F3811": 902637.0,
            "F3487": -0.94,
            "F3889": "G365D",
            "F2752": -0.31,
            "F3806": 668881.0,
            "F2678": -0.11,
            "F2782": 0.0,
            "F3240": -1.0,
            "F2890": 47.0,
            "F2737": -0.15,
            "F1041": 0.0,
            "F1814": 1000000.0,
            "F2938": 43.0,
            "F997": 30000.0,
            "F2956": 65.0,
            "F3813": 457023.6,
            "F3914": 0.0,
            "F1594": 31.0,
            "F2236": 0.0,
            "F3495": -0.87,
            "F2488": 2.03,
            "F120": 0.63,
            "F1936": 0.0,
            "F937": 0.0,
            "F1603": 759856.0,
            "F321": 1.06,
            "F3894": 37.0,
            "F1815": 887994.54,
            "F3920": 0.0,
            "F3824": 0.46297,
            "F3484": 0.02,
            "F3490": 0.03,
            "F261": 0.3,
            "F427": 1.085,
            "F991": 65023.0,
            "F3900": 0.0,
            "F18": 0.73,
            "F996": 1.0,
            "F2825": -0.36,
            "F1692": 0.0,
            "F2137": 23555.07512,
            "F531": 1.2,
            "F1597": 876567.87,
            "F1954": 0.0,
            "F3043": 85.0,
            "F3805": 1331230.0,
            "F1642": 16.0,
            "F1746": 0.0,
            "F510": 1.0,
            "F1209": 0.0,
            "F3801": 840290.99,
            "F2786": -0.09,
            "F1001": 0.0,
            "F378": 1.02,
            "F115": 0.52,
            "F3871": 183803.75,
            "F1921": 30518.27273,
            "F1639": 184500.0,
            "F373": 1.025,
            "F2645": -0.1,
            "F2686": -0.12,
            "F2735": 0.0,
            "F1015": 0.0,
            "F3887": 105.0,
            "F463": 1.08,
            "F670": 0.0,
            "F2068": 0.10491935499999999,
            "F1112": 5498.34,
            "F1058": 156167.5,
            "F2584": -0.1,
            "F2724": -0.19,
            "F164": 0.5,
            "F2885": 43.0,
            "F1273": 165393.48,
            "F3836": 438685.51,
            "F3868": 1.0,
            "F3150": -1.0,
            "F3804": 30.0,
            "F274": 0.28,
            "F2282": 0.56,
            "F2489": 1.59,
            "F235": 0.18,
            "F2392": 0.8,
            "F3526": -0.645,
            "F3494": -0.97,
            "F2991": 71.0,
            "F3872": 191581.915,
            "F3908": 0.0,
            "F3485": -0.28,
            "F2796": -0.165,
            "F54": 0.56,
            "F1821": 840248.44,
            "F327": 1.07,
            "F2998": 77.0,
            "F3921": 0.0,
            "F465": 1.05,
            "F1705": 1322317.13,
            "F3798": 53.0,
            "F3348": -1.0,
            "F3642": 0.16,
            "F2883": 42.0,
            "F3891": "salaried",
            "F408": 1.0,
            "F3534": 0.14,
            "F2691": -0.16,
            "F2242": 0.325,
            "F3598": 0.03,
            "F527": 1.0,
            "F2799": -0.245,
            "F3105": 135.0,
            "F2736": 0.0,
            "F2591": -0.15,
            "F2078": 392.87784645,
            "F2551": -0.21,
            "F322": 1.05,
            "F2388": 0.68,
            "F2586": -0.13,
            "F2484": 2.49,
            "F3825": 0.496223,
            "F2772": -0.46,
            "F3395": -1.0,
            "F2350": 0.6,
            "F1057": 220000.0,
            "F3143": 81.0,
            "F1813": 1926111.9,
            "F3886": "Savings",
            "F951": 100000.0,
            "F1381": 199999.245,
            "F3643": -0.35,
            "F2082": 0.0,
            "F374": 1.06,
            "F1744": 4.0,
            "F3647": -0.87,
            "F2527": 0.0,
            "F1489": 243177.5,
            "F336": 1.01,
            "F228": 0.41,
            "F2896": 45.5,
            "F2999": 68.0,
            "F366": 1.0,
            "F2122": 0.0,
            "F2077": 3096.4921305,
            "F471": 1.13,
            "F2070": 0.0,
            "F3898": 2.0,
            "F1167": 100000.0,
            "F2640": 0.0,
            "F270": 0.39,
            "F2595": -0.08499999999999999,
            "F367": 1.1,
            "F1153": 0.0,
            "F156": 0.59,
            "F3287": -1.0,
            "F3704": -0.96,
            "F1707": 612330.12,
            "F64": 0.69,
            "F2582": 0.0,
            "F2494": 1.5750000000000002,
            "F112": 0.665,
            "F2680": -0.09,
            "F2848": 38.0,
            "F2391": 0.71,
            "F949": 200000.0,
            "F1165": 259849.0,
            "F3907": 0.0,
            "F3799": 1839602.0,
            "F3838": 140026.32
        },
        "clean_selfemployed": {
            "F1923": 11416.2,
            "F3811": 982985.0,
            "F3487": -0.94,
            "F3889": "G365D",
            "F2752": -0.325,
            "F3806": 709021.0,
            "F2678": -0.12,
            "F2782": 0.0,
            "F3240": -1.0,
            "F2890": 46.0,
            "F2737": -0.14,
            "F1041": 0.0,
            "F1814": 918985.0,
            "F2938": 49.0,
            "F997": 28500.0,
            "F2956": 63.0,
            "F3813": 505708.32,
            "F3914": 0.0,
            "F1594": 32.0,
            "F2236": 0.0,
            "F3495": -0.87,
            "F2488": 1.895,
            "F120": 0.64,
            "F1936": 0.0,
            "F937": 0.0,
            "F1603": 683901.9,
            "F321": 1.07,
            "F3894": 33.0,
            "F1815": 807798.59,
            "F3920": 0.0,
            "F3824": 0.447192,
            "F3484": 0.03,
            "F3490": 0.03,
            "F261": 0.3,
            "F427": 1.09,
            "F991": 56369.0,
            "F3900": 0.0,
            "F18": 0.74,
            "F996": 1.0,
            "F2825": -0.44,
            "F1692": 0.0,
            "F2137": 22027.71358,
            "F531": 1.2,
            "F1597": 809007.82,
            "F1954": 0.0,
            "F3043": 88.0,
            "F3805": 1425709.0,
            "F1642": 16.0,
            "F1746": 0.0,
            "F510": 1.0,
            "F1209": 0.0,
            "F3801": 945976.0,
            "F2786": -0.08,
            "F1001": 0.0,
            "F378": 1.02,
            "F115": 0.52,
            "F3871": 170983.0,
            "F1921": 27727.27273,
            "F1639": 166023.48,
            "F373": 1.08,
            "F2645": -0.09,
            "F2686": -0.11,
            "F2735": 0.0,
            "F1015": 0.0,
            "F3887": 75.0,
            "F463": 1.08,
            "F670": 0.0,
            "F2068": 0.104477612,
            "F1112": 670.0,
            "F1058": 132980.0,
            "F2584": -0.1,
            "F2724": -0.215,
            "F164": 0.5,
            "F2885": 44.0,
            "F1273": 137950.0,
            "F3836": 389757.04,
            "F3868": 1.0,
            "F3150": -1.0,
            "F3804": 30.0,
            "F274": 0.3,
            "F2282": 0.585,
            "F2489": 1.47,
            "F235": 0.135,
            "F2392": 0.92,
            "F3526": -0.6,
            "F3494": -0.97,
            "F2991": 69.0,
            "F3872": 174044.0,
            "F3908": 0.0,
            "F3485": -0.25,
            "F2796": -0.13,
            "F54": 0.57,
            "F1821": 778932.5,
            "F327": 1.08,
            "F2998": 75.0,
            "F3921": 0.0,
            "F465": 1.03,
            "F1705": 1192865.76,
            "F3798": 50.0,
            "F3348": -1.0,
            "F3642": 0.05,
            "F2883": 41.0,
            "F3891": "selfemployed",
            "F408": 1.0,
            "F3534": 0.01,
            "F2691": -0.17,
            "F2242": 0.295,
            "F3598": 0.03,
            "F527": 1.0,
            "F2799": -0.21,
            "F3105": 134.0,
            "F2736": 0.0,
            "F2591": -0.14,
            "F2078": 528.8235294,
            "F2551": -0.21,
            "F322": 1.06,
            "F2388": 0.65,
            "F2586": -0.13,
            "F2484": 2.38,
            "F3825": 0.482345,
            "F2772": -0.38,
            "F3395": -1.0,
            "F2350": 0.58,
            "F1057": 200000.0,
            "F3143": 76.0,
            "F1813": 1749057.82,
            "F3886": "Current",
            "F951": 98252.0,
            "F1381": 189394.5,
            "F3643": -0.34,
            "F2082": 0.0,
            "F374": 1.08,
            "F1744": 4.0,
            "F3647": -0.88,
            "F2527": -0.1,
            "F1489": 205395.0,
            "F336": 1.0,
            "F228": 0.42,
            "F2896": 42.5,
            "F2999": 67.0,
            "F366": 1.0,
            "F2122": 0.0,
            "F2077": 3267.805263,
            "F471": 1.11,
            "F2070": 0.0,
            "F3898": 3.0,
            "F1167": 100000.0,
            "F2640": 0.0,
            "F270": 0.4,
            "F2595": -0.05,
            "F367": 1.09,
            "F1153": 0.0,
            "F156": 0.6,
            "F3287": -1.0,
            "F3704": -0.96,
            "F1707": 558770.0,
            "F64": 0.69,
            "F2582": 0.0,
            "F2494": 1.58,
            "F112": 0.66,
            "F2680": -0.08,
            "F2848": 37.0,
            "F2391": 0.78,
            "F949": 165206.0,
            "F1165": 249410.0,
            "F3907": 0.0,
            "F3799": 1967879.6,
            "F3838": 127561.0
        },
        "mule_selfemployed": {
            "F1923": 2718.9200535,
            "F3811": 123505.43,
            "F3487": -0.99,
            "F3889": "G365D",
            "F2752": 0.0,
            "F3806": 65897.35,
            "F2678": -0.015,
            "F2782": 0.0,
            "F3240": -1.0,
            "F2890": 22.0,
            "F2737": -0.02,
            "F1041": 0.0,
            "F1814": 76221.85,
            "F2938": 27.0,
            "F997": 20750.0,
            "F2956": 44.0,
            "F3813": 87112.0,
            "F3914": 0.0,
            "F1594": 20.0,
            "F2236": 0.875,
            "F3495": -0.99,
            "F2488": 0.75,
            "F120": 0.995,
            "F1936": 0.0,
            "F937": 0.0,
            "F1603": 121204.64,
            "F321": 1.0,
            "F3894": 33.5,
            "F1815": 119604.59,
            "F3920": 0.0,
            "F3824": 0.583858,
            "F3484": 0.04,
            "F3490": 0.06,
            "F261": 1.0,
            "F427": 1.0,
            "F991": 5390.0,
            "F3900": 0.0,
            "F18": 0.92,
            "F996": 1.0,
            "F2825": -0.05,
            "F1692": 0.0,
            "F2137": 3787.2659155,
            "F531": 1.11,
            "F1597": 121204.64,
            "F1954": 0.0,
            "F3043": 63.0,
            "F3805": 154533.28,
            "F1642": 19.0,
            "F1746": 0.0,
            "F510": 1.39,
            "F1209": 0.0,
            "F3801": 133882.065,
            "F2786": 0.0,
            "F1001": 0.0,
            "F378": 0.72,
            "F115": 0.905,
            "F3871": 65356.5,
            "F1921": 4369.6794875000005,
            "F1639": 6725.0,
            "F373": 0.975,
            "F2645": -0.01,
            "F2686": 0.0,
            "F2735": 0.0,
            "F1015": 0.0,
            "F3887": 78.5,
            "F463": 1.01,
            "F670": 0.0,
            "F2068": 0.0410569105,
            "F1112": 0.0,
            "F1058": 31500.495,
            "F2584": 0.0,
            "F2724": -0.425,
            "F164": 0.94,
            "F2885": 43.5,
            "F1273": 26474.5,
            "F3836": 419660.895,
            "F3868": 1.0,
            "F3150": -1.0,
            "F3804": 26.5,
            "F274": 0.375,
            "F2282": 0.0,
            "F2489": 0.125,
            "F235": 0.565,
            "F2392": 0.07,
            "F3526": -0.88,
            "F3494": -0.99,
            "F2991": 48.5,
            "F3872": 65356.5,
            "F3908": 1.0,
            "F3485": -0.525,
            "F2796": 0.825,
            "F54": 0.8,
            "F1821": 119604.59,
            "F327": 1.0,
            "F2998": 45.0,
            "F3921": 0.0,
            "F465": 1.0,
            "F1705": 148725.5,
            "F3798": 38.5,
            "F3348": -1.0,
            "F3642": 2.75,
            "F2883": 40.0,
            "F3891": "selfemployed",
            "F408": 1.07,
            "F3534": 2.9,
            "F2691": -0.005,
            "F2242": 1.935,
            "F3598": 0.055,
            "F527": 1.0,
            "F2799": 1.315,
            "F3105": 51.5,
            "F2736": 0.005,
            "F2591": 0.01,
            "F2078": 1418.1190474999999,
            "F2551": 0.0,
            "F322": 1.0,
            "F2388": 0.01,
            "F2586": -0.01,
            "F2484": 0.48,
            "F3825": 0.8191485000000001,
            "F2772": -0.37,
            "F3395": -1.0,
            "F2350": 0.005,
            "F1057": 33650.0,
            "F3143": 17.0,
            "F1813": 178912.9,
            "F3886": "Savings",
            "F951": 20000.0,
            "F1381": 32650.0,
            "F3643": -0.37,
            "F2082": 0.0,
            "F374": 0.975,
            "F1744": 1.0,
            "F3647": -1.0,
            "F2527": 0.039999999999999994,
            "F1489": 37393.994999999995,
            "F336": 0.905,
            "F228": 0.845,
            "F2896": 29.0,
            "F2999": 44.0,
            "F366": 1.0,
            "F2122": 0.0,
            "F2077": 3049.1166665,
            "F471": 1.0,
            "F2070": 0.0,
            "F3898": 1.0,
            "F1167": 20000.0,
            "F2640": 0.0,
            "F270": 0.895,
            "F2595": 0.63,
            "F367": 1.0,
            "F1153": 0.0,
            "F156": 1.0,
            "F3287": -1.0,
            "F3704": -0.995,
            "F1707": 91054.0,
            "F64": 0.935,
            "F2582": 0.0,
            "F2494": 0.905,
            "F112": 0.97,
            "F2680": 0.0,
            "F2848": 22.0,
            "F2391": 0.07,
            "F949": 26500.0,
            "F1165": 37394.0,
            "F3907": 0.0,
            "F3799": 203247.4,
            "F3838": 59469.229999999996
        }
    }
}